overtake/__init__.py
overtake/decorator.py
overtake/display_objects.py
overtake/incompatibility_reasons.py
overtake/lazy_inspection.py
overtake/overtake_class.py
overtake/py.typed
overtake/runtime_type_checkers/__init__.py
overtake/runtime_type_checkers/basic.py
overtake/runtime_type_checkers/beartype_is_bearable.py
overtake/runtime_type_checkers/pydantic_type_adapter.py
overtake/runtime_type_checkers/umbrella.py
overtake-0.4.0.dist-info/METADATA
overtake-0.4.0.dist-info/WHEEL
overtake-0.4.0.dist-info/licenses/LICENSE
overtake-0.4.0.dist-info/RECORD
