Metadata-Version: 2.1
Name: overtake
Version: 0.4.0
Summary: A runtime implementation of @typing.overload.
Author-email: Gabriel de Marmiesse <gabrieldemarmiesse@gmail.com>
License: MIT
License-File: LICENSE
Requires-Python: >=3.8
Requires-Dist: typing-extensions<5,>=4.7.0
Provides-Extra: beartype
Requires-Dist: beartype<1,>=0.12.0; extra == 'beartype'
Provides-Extra: pydantic
Requires-Dist: pydantic<3,>=2.0; extra == 'pydantic'
